common_cols_project/__init__.py
common_cols_project/common_cols_project.py
common_cols_project-0.1.3.dist-info/METADATA
common_cols_project-0.1.3.dist-info/WHEEL
common_cols_project-0.1.3.dist-info/top_level.txt
common_cols_project-0.1.3.dist-info/RECORD
