Metadata-Version: 2.1
Name: common-cols-project
Version: 0.1.3
Summary: Given a list of data frames, finds common columns between all pairs of data frames.
Home-page: https://github.com/ElenaGarciaManes?tab=repositories
Author: Elena García Mañes
Author-email: elenagarciamanes@example.com
License: UNKNOWN
Platform: UNKNOWN
Classifier: Programming Language :: Python :: 3
Classifier: License :: OSI Approved :: MIT License
Classifier: Operating System :: OS Independent
Requires-Python: >=3.6
